xrouter/__init__.py
xrouter/__version__.py
xrouter-0.0.1.dist-info/LICENSE
xrouter-0.0.1.dist-info/METADATA
xrouter-0.0.1.dist-info/WHEEL
xrouter-0.0.1.dist-info/top_level.txt
xrouter-0.0.1.dist-info/zip-safe
xrouter-0.0.1.dist-info/RECORD
