Metadata-Version: 2.1
Name: xrouter
Version: 0.0.1
Summary: XRouter
Home-page: https://github.com/ertgl/xrouter/
Author: Ertuğrul Noyan Keremoğlu
Author-email: ertugkeremoglu@gmail.com
License: MIT
Classifier: Intended Audience :: Developers
Classifier: License :: OSI Approved :: MIT License
Classifier: Natural Language :: English
Classifier: Operating System :: OS Independent
Classifier: Programming Language :: Python :: 3
Classifier: Topic :: Software Development :: Libraries :: Python Modules
Classifier: Topic :: Utilities
Classifier: Typing :: Typed
License-File: LICENSE
